drf_keyed_list/__init__.py
drf_keyed_list/serializers.py
drf_keyed_list-0.0.2.dist-info/LICENSE.md
drf_keyed_list-0.0.2.dist-info/METADATA
drf_keyed_list-0.0.2.dist-info/WHEEL
drf_keyed_list-0.0.2.dist-info/top_level.txt
drf_keyed_list-0.0.2.dist-info/RECORD
