Metadata-Version: 2.1
Name: drf-keyed-list
Version: 0.0.2
Summary: UNKNOWN
Home-page: http://github.com/claytondaley/drf-keyed-list
Author: Clayton Daley III
Author-email: clayton.daley+github@gmail.com
License: Apache 2.0
Keywords: drf restframework rest_framework django_rest_framework serializers drf_mapped_nested
Platform: UNKNOWN
Classifier: Development Status :: 3 - Alpha
Classifier: Environment :: Web Environment
Classifier: Framework :: Django
Classifier: Framework :: Django :: 1.9
Classifier: Framework :: Django :: 1.10
Classifier: Framework :: Django :: 1.11
Classifier: Framework :: Django :: 2.0
Classifier: Intended Audience :: Developers
Classifier: License :: OSI Approved :: Apache Software License
Classifier: Operating System :: OS Independent
Classifier: Programming Language :: Python
Classifier: Programming Language :: Python :: 3
Classifier: Programming Language :: Python :: 3.3
Classifier: Programming Language :: Python :: 3.4
Classifier: Programming Language :: Python :: 3.5
Classifier: Topic :: Internet :: WWW/HTTP
